fluentcms_emailtemplates/__init__.py
fluentcms_emailtemplates/admin.py
fluentcms_emailtemplates/conf.py
fluentcms_emailtemplates/extensions.py
fluentcms_emailtemplates/managers.py
fluentcms_emailtemplates/models.py
fluentcms_emailtemplates/rendering.py
fluentcms_emailtemplates/shortcuts.py
fluentcms_emailtemplates/views.py
fluentcms_emailtemplates/locale/nl/LC_MESSAGES/django.mo
fluentcms_emailtemplates/locale/nl/LC_MESSAGES/django.po
fluentcms_emailtemplates/migrations/0001_initial.py
fluentcms_emailtemplates/migrations/__init__.py
fluentcms_emailtemplates/plugins/__init__.py
fluentcms_emailtemplates/plugins/emailtext/__init__.py
fluentcms_emailtemplates/plugins/emailtext/content_plugins.py
fluentcms_emailtemplates/plugins/emailtext/models.py
fluentcms_emailtemplates/plugins/emailtext/migrations/0001_initial.py
fluentcms_emailtemplates/plugins/emailtext/migrations/__init__.py
fluentcms_emailtemplates/plugins/emailtext/south_migrations/0001_initial.py
fluentcms_emailtemplates/plugins/emailtext/south_migrations/__init__.py
fluentcms_emailtemplates/plugins/emailtext/templates/admin/fluentcms_emailtemplates/plugins/emailtext/admin_init.html
fluentcms_emailtemplates/plugins/oscar_email/__init__.py
fluentcms_emailtemplates/plugins/oscar_email/content_plugins.py
fluentcms_emailtemplates/plugins/oscar_email/models.py
fluentcms_emailtemplates/plugins/oscar_email/migrations/0001_initial.py
fluentcms_emailtemplates/plugins/oscar_email/migrations/__init__.py
fluentcms_emailtemplates/plugins/oscar_email/south_migrations/0001_initial.py
fluentcms_emailtemplates/plugins/oscar_email/south_migrations/__init__.py
fluentcms_emailtemplates/plugins/oscar_email/templates/fluentcms_emailtemplates/plugins/oscar_email/order_summary.html
fluentcms_emailtemplates/plugins/oscar_email/templates/fluentcms_emailtemplates/plugins/oscar_email/order_summary.txt
fluentcms_emailtemplates/static/fluentcms_emailtemplates/admin/preview.css
fluentcms_emailtemplates-2.0.dist-info/DESCRIPTION.rst
fluentcms_emailtemplates-2.0.dist-info/METADATA
fluentcms_emailtemplates-2.0.dist-info/RECORD
fluentcms_emailtemplates-2.0.dist-info/WHEEL
fluentcms_emailtemplates-2.0.dist-info/metadata.json
fluentcms_emailtemplates-2.0.dist-info/top_level.txt
