Metadata-Version: 2.0
Name: fluentcms-emailtemplates
Version: 2.0
Summary: Creating e-mail messages, with multiple layouts and multilingual content.
Home-page: https://github.com/edoburu/fluentcms-emailtemplates
Author: Diederik van der Boor
Author-email: opensource@edoburu.nl
License: Apache 2.0
Download-URL: https://github.com/edoburu/fluentcms-emailtemplates/zipball/master
Platform: UNKNOWN
Classifier: Development Status :: 4 - Beta
Classifier: Environment :: Web Environment
Classifier: Framework :: Django
Classifier: Intended Audience :: Developers
Classifier: License :: OSI Approved :: Apache Software License
Classifier: Operating System :: OS Independent
Classifier: Programming Language :: Python
Classifier: Programming Language :: Python :: 2.6
Classifier: Programming Language :: Python :: 2.7
Classifier: Programming Language :: Python :: 3
Classifier: Programming Language :: Python :: 3.3
Classifier: Framework :: Django
Classifier: Framework :: Django :: 1.4
Classifier: Framework :: Django :: 1.5
Classifier: Framework :: Django :: 1.6
Classifier: Framework :: Django :: 1.7
Classifier: Framework :: Django :: 1.8
Classifier: Topic :: Internet :: WWW/HTTP
Classifier: Topic :: Internet :: WWW/HTTP :: Dynamic Content
Classifier: Topic :: Software Development :: Libraries :: Python Modules
Requires: Django (>=1.4)
Requires-Dist: django-fluent-contents (>=1.0.2)
Requires-Dist: django-fluent-utils (>=1.2.1)
Requires-Dist: django-appconf (>=1.0)
Requires-Dist: django-parler (>=1.4)
Requires-Dist: beautifulsoup4 (>=4.3.2)
Requires-Dist: html2text (>=2015.6.12)
